to_tmx/__init__.py
to_tmx/sent_tok.py
to_tmx/tmx_batch_tradosizer.py
to_tmx/tmx_tradosizer.py
to_tmx/to_tmx.py
to_tmx-1.0.3.dist-info/LICENSE.txt
to_tmx-1.0.3.dist-info/METADATA
to_tmx-1.0.3.dist-info/WHEEL
to_tmx-1.0.3.dist-info/entry_points.txt
to_tmx-1.0.3.dist-info/top_level.txt
to_tmx-1.0.3.dist-info/RECORD
