Metadata-Version: 2.1
Name: to-tmx
Version: 1.0.3
Summary: Txt-to-tmx file converter.
Home-page: https://github.com/AlexSkrn/to_tmx
Author: AlexSkrn
Author-email: alex.g.skrn@gmail.com
License: MIT
Keywords: tmx converter
Platform: UNKNOWN
Classifier: License :: OSI Approved :: MIT License
Classifier: Programming Language :: Python
Classifier: Programming Language :: Python :: 3
Requires-Python: >=3.6.0
License-File: LICENSE.txt
Requires-Dist: setuptools (>=47.1.1)
Requires-Dist: wheel (>=0.34.2)
Requires-Dist: nltk (>=3.5)
